datapizza/clients/anthropic/__init__.py
datapizza/clients/anthropic/anthropic_client.py
datapizza/clients/anthropic/memory_adapter.py
datapizza_ai_clients_anthropic-0.0.3.dist-info/METADATA
datapizza_ai_clients_anthropic-0.0.3.dist-info/WHEEL
datapizza_ai_clients_anthropic-0.0.3.dist-info/RECORD
